maksim_132_servo/__init__.py
maksim_132_servo/main.py
maksim_132_servo-0.1.2.dist-info/METADATA
maksim_132_servo-0.1.2.dist-info/WHEEL
maksim_132_servo-0.1.2.dist-info/licenses/LICENSE
maksim_132_servo-0.1.2.dist-info/RECORD
