Metadata-Version: 2.4
Name: maksim_132_servo
Version: 0.1.2
Summary: Library for controlling servo motor via Arduino with Telegram bot support
Author-email: Максим Рогов <your.email@example.com>
License-Expression: MIT
License-File: LICENSE
Classifier: Development Status :: 4 - Beta
Classifier: Intended Audience :: Developers
Classifier: License :: OSI Approved :: MIT License
Classifier: Operating System :: OS Independent
Classifier: Programming Language :: Python :: 3
Classifier: Topic :: Home Automation
Classifier: Topic :: Software Development :: Libraries :: Python Modules
Requires-Python: >=3.7
Requires-Dist: pyserial>=3.5
Requires-Dist: python-telegram-bot>=20.0
Provides-Extra: dev
Requires-Dist: black>=22.0.0; extra == 'dev'
Requires-Dist: flake8>=4.0.0; extra == 'dev'
Requires-Dist: pytest>=6.0.0; extra == 'dev'
